experiment_design/__init__.py
experiment_design/covariance_modification.py
experiment_design/experiment_designer.py
experiment_design/optimize.py
experiment_design/orthogonal_sampling.py
experiment_design/random_sampling.py
experiment_design/scorers.py
experiment_design/variable/__init__.py
experiment_design/variable/space.py
experiment_design/variable/variable.py
experiment_design-0.1.4.dist-info/LICENSE
experiment_design-0.1.4.dist-info/METADATA
experiment_design-0.1.4.dist-info/WHEEL
experiment_design-0.1.4.dist-info/RECORD
