Metadata-Version: 2.3
Name: experiment-design
Version: 0.1.4
Summary: Tools to create designs of experiments
License: MIT
Author: Can Bogoclu
Requires-Python: >=3.10,<4.0
Classifier: License :: OSI Approved :: MIT License
Classifier: Programming Language :: Python :: 3
Classifier: Programming Language :: Python :: 3.10
Classifier: Programming Language :: Python :: 3.11
Classifier: Programming Language :: Python :: 3.12
Classifier: Programming Language :: Python :: 3.13
Requires-Dist: numpy (>=2.1.0,<3.0.0)
Requires-Dist: scipy (>=1.14.1,<2.0.0)
Project-URL: Documentation, https://experiment-design.readthedocs.io
Project-URL: Homepage, https://experiment-design.readthedocs.io
Project-URL: Repository, https://github.com/canbooo/experiment-design
